hms_commander/Atlas14Storm.py
hms_commander/Decorators.py
hms_commander/FrequencyStorm.py
hms_commander/HmsAorc.py
hms_commander/HmsBasin.py
hms_commander/HmsCmdr.py
hms_commander/HmsControl.py
hms_commander/HmsExamples.py
hms_commander/HmsGage.py
hms_commander/HmsGeo.py
hms_commander/HmsGrid.py
hms_commander/HmsHuc.py
hms_commander/HmsJython.py
hms_commander/HmsM3Model.py
hms_commander/HmsMet.py
hms_commander/HmsOutput.py
hms_commander/HmsPrj.py
hms_commander/HmsResults.py
hms_commander/HmsRun.py
hms_commander/HmsUtils.py
hms_commander/LoggingConfig.py
hms_commander/ScsTypeStorm.py
hms_commander/__init__.py
hms_commander/_constants.py
hms_commander/_parsing.py
hms_commander/data/README.md
hms_commander/data/__init__.py
hms_commander/data/m3_hms_catalog.csv
hms_commander/data/scs_type_i.npy
hms_commander/data/scs_type_ia.npy
hms_commander/data/scs_type_ii.npy
hms_commander/data/scs_type_iii.npy
hms_commander/data/tp40_dimensionless_pattern.npy
hms_commander/dss/__init__.py
hms_commander/dss/_hec_monolith.py
hms_commander/dss/core.py
hms_commander/dss/hms_dss.py
hms_commander/dss/hms_dss_grid.py
hms_commander-0.2.0.dist-info/licenses/LICENSE
hms_commander-0.2.0.dist-info/METADATA
hms_commander-0.2.0.dist-info/WHEEL
hms_commander-0.2.0.dist-info/top_level.txt
hms_commander-0.2.0.dist-info/RECORD
