Metadata-Version: 2.4
Name: hms-commander
Version: 0.2.0
Summary: HEC-HMS automation library for hydrologic modeling - Python API for project management, simulation execution, and results analysis
Author-email: "William Katzenmeyer, PE, CFM" <billk@clbengineering.com>
License-Expression: MIT
Project-URL: Homepage, https://github.com/gpt-cmdr/hms-commander
Project-URL: Documentation, https://gpt-cmdr.github.io/hms-commander/
Project-URL: Repository, https://github.com/gpt-cmdr/hms-commander
Project-URL: Issues, https://github.com/gpt-cmdr/hms-commander/issues
Keywords: HEC-HMS,hydrology,hydrologic modeling,water resources,engineering,automation,simulation,DSS,GIS
Classifier: Development Status :: 3 - Alpha
Classifier: Intended Audience :: Science/Research
Classifier: Intended Audience :: Developers
Classifier: Operating System :: Microsoft :: Windows
Classifier: Programming Language :: Python :: 3
Classifier: Programming Language :: Python :: 3.10
Classifier: Programming Language :: Python :: 3.11
Classifier: Programming Language :: Python :: 3.12
Classifier: Topic :: Scientific/Engineering :: GIS
Classifier: Topic :: Scientific/Engineering :: Hydrology
Requires-Python: >=3.10
License-File: LICENSE
Requires-Dist: pandas>=1.5.0
Requires-Dist: numpy>=1.21.0
Requires-Dist: pathlib
Requires-Dist: tqdm
Requires-Dist: requests
Provides-Extra: dev
Requires-Dist: pytest>=7.0; extra == "dev"
Requires-Dist: black>=22.0; extra == "dev"
Requires-Dist: flake8>=4.0; extra == "dev"
Requires-Dist: jupyter; extra == "dev"
Provides-Extra: gis
Requires-Dist: geopandas>=0.12.0; extra == "gis"
Requires-Dist: pyproj>=3.3.0; extra == "gis"
Requires-Dist: shapely>=2.0.0; extra == "gis"
Requires-Dist: pynhd>=0.19.0; extra == "gis"
Requires-Dist: pygeohydro>=0.19.0; extra == "gis"
Provides-Extra: dss
Requires-Dist: ras-commander>=0.83.0; extra == "dss"
Requires-Dist: pyjnius; extra == "dss"
Provides-Extra: aorc
Requires-Dist: xarray>=2023.1.0; extra == "aorc"
Requires-Dist: zarr>=2.13.0; extra == "aorc"
Requires-Dist: s3fs>=2023.1.0; extra == "aorc"
Requires-Dist: netCDF4>=1.6.0; extra == "aorc"
Requires-Dist: rioxarray>=0.13.0; extra == "aorc"
Provides-Extra: docs
Requires-Dist: mkdocs>=1.5.0; extra == "docs"
Requires-Dist: mkdocs-material>=9.0.0; extra == "docs"
Requires-Dist: mkdocstrings[python]>=0.24.0; extra == "docs"
Requires-Dist: mkdocs-jupyter>=0.24.0; extra == "docs"
Requires-Dist: mkdocs-git-revision-date-localized-plugin>=1.2.0; extra == "docs"
Provides-Extra: all
Requires-Dist: hms-commander[aorc,dev,docs,dss,gis]; extra == "all"
Dynamic: license-file
